{
  "required": true,
  "package": "carpetlunaaraddons.mixins",
  "compatibilityLevel": "JAVA_8",
  "mixins": [
    "CarpetServerMixin",
    "DrownedEntityMixin",
    "EnderPearlEntityMixin",
    "MobEntityMixin",
    "PhantomSpawnerMixin",
    "PlayerEntityMixin",
    "PortalForcerMixin",
    "ServerChunkManagerMixin",
    "SpawnHelperMixin",
    "TridentEntityMixin",
    "accessors.EntityAccessorMixin",
    "accessors.PersistentProjectileEntityAccessorMixin"
  ],
  "client": [
  ],
  "injectors": {
    "defaultRequire": 1
  }
}
